simple_nlp_library/__init__.py
simple_nlp_library/embeddings.py
simple_nlp_library/metrics.py
simple_nlp_library/preprocessing.py
simple_nlp_library/data/glove.6B.50d.txt
simple_nlp_library/data/pddl-10.txt
simple_nlp_library/data/scikitlearn.txt
simple_nlp_library-4.0.0.dist-info/METADATA
simple_nlp_library-4.0.0.dist-info/WHEEL
simple_nlp_library-4.0.0.dist-info/licenses/LICENSE
simple_nlp_library-4.0.0.dist-info/RECORD
