Metadata-Version: 2.1
Name: simple-nlp-library
Version: 4.0.0
Summary: Simple NLP library
Project-URL: Homepage, https://github.com/marekm4/simple_nlp_library
Project-URL: Bug Tracker, https://github.com/marekm4/simple_nlp_library/issues
Author-email: Marek Michalik <marekmichalik43@gmail.com>
License-File: LICENSE
Classifier: License :: OSI Approved :: MIT License
Classifier: Operating System :: OS Independent
Classifier: Programming Language :: Python :: 3
Classifier: Topic :: Scientific/Engineering :: Artificial Intelligence
Requires-Python: >=3.7
